itk/Configuration/TubeTKConfig.py
itk/Configuration/TubeTK_snake_case.py
itk/TubeTKPython.py
itk/_TubeTKPython.abi3.so
itk/tubeComputeBinaryImageSimilarityMetricsPython.py
itk/tubeComputeImageSimilarityMetricsPython.py
itk/tubeComputeImageStatisticsPython.py
itk/tubeComputeTrainingMaskPython.py
itk/tubeComputeTubeFlyThroughImagePython.py
itk/tubeComputeTubeMeasuresPython.py
itk/tubeConvertImagesToCSVFilterPython.py
itk/tubeConvertShrunkenSeedImageToListPython.py
itk/tubeConvertSpatialGraphToImagePython.py
itk/tubeConvertTubesToDensityImagePython.py
itk/tubeConvertTubesToImagePython.py
itk/tubeConvertTubesToTubeGraphPython.py
itk/tubeCropImagePython.py
itk/tubeCropTubesPython.py
itk/tubeEnhanceContrastUsingPriorPython.py
itk/tubeEnhanceEdgesUsingDiffusionPython.py
itk/tubeEnhanceTubesUsingDiffusionPython.py
itk/tubeEnhanceTubesUsingDiscriminantAnalysisPython.py
itk/tubeImageMathPython.py
itk/tubeMergeAdjacentImagesPython.py
itk/tubeRegisterImagesPython.py
itk/tubeResampleImagePython.py
itk/tubeSegmentBinaryImageSkeleton3DPython.py
itk/tubeSegmentConnectedComponentsPython.py
itk/tubeSegmentConnectedComponentsUsingParzenPDFsPython.py
itk/tubeSegmentTubeUsingMinimalPathPython.py
itk/tubeSegmentTubesPython.py
itk/tubeSegmentUsingOtsuThresholdPython.py
itk/tubeShrinkImageWithBlendingPython.py
itk/tubeTubeMathPython.py
itk/tubeWrite4DImageFrom3DImagesPython.py
itk_tubetk-1.4.1.dist-info/METADATA
itk_tubetk-1.4.1.dist-info/WHEEL
itk_tubetk-1.4.1.dist-info/licenses/LICENSE
itk_tubetk-1.4.1.dist-info/RECORD
