Metadata-Version: 2.1
Name: itk-tubetk
Version: 1.4.1
Summary: An open-source toolkit, led by Kitware, Inc., for the segmentation, registration, and analysis of tubes (e.g., blood vessels) in images.
Keywords: itk,InsightToolkit,Tubes,Vessels,Nerves,Ultrasound,MRI,CT,Medical
Author-Email: "Stephen R. Aylward" <stephen.aylward@kitware.com>
License: 
Classifier: Development Status :: 4 - Beta
Classifier: Intended Audience :: Developers
Classifier: Intended Audience :: Education
Classifier: Intended Audience :: Healthcare Industry
Classifier: Intended Audience :: Science/Research
Classifier: License :: OSI Approved :: Apache Software License
Classifier: Operating System :: MacOS
Classifier: Operating System :: Microsoft :: Windows
Classifier: Operating System :: POSIX
Classifier: Operating System :: Unix
Classifier: Programming Language :: C++
Classifier: Programming Language :: Python
Classifier: Topic :: Scientific/Engineering
Classifier: Topic :: Scientific/Engineering :: Information Analysis
Classifier: Topic :: Scientific/Engineering :: Medical Science Apps.
Classifier: Topic :: Software Development :: Libraries
Project-URL: Download, https://github.com/InsightSoftwareConsortium/ITKTubeTK
Project-URL: Homepage, https://github.com/InsightSoftwareConsortium/ITKTubeTK
Project-URL: Repository, https://github.com/InsightSoftwareConsortium/ITKTubeTK
Project-URL: Issues, https://github.com/InsightSoftwareConsortium/ITKTubeTK/issues
Requires-Python: >=3.9
Requires-Dist: itk==5.4.*
Requires-Dist: numpy
Requires-Dist: itk-minimalpathextraction>=1.2.6
Provides-Extra: doc
Requires-Dist: recommonmark; extra == "doc"
Requires-Dist: Sphinx==3.3.0; extra == "doc"
Requires-Dist: sphinx-rtd-theme==0.5.0; extra == "doc"
Requires-Dist: sphinx-autodoc-typehints==1.11.1; extra == "doc"
Requires-Dist: typing-extensions; extra == "doc"
